setup.py
Leonov_1279/__init__.py
Leonov_1279/abc.py
Leonov_1279/dee.py
Leonov_1279.egg-info/PKG-INFO
Leonov_1279.egg-info/SOURCES.txt
Leonov_1279.egg-info/dependency_links.txt
Leonov_1279.egg-info/top_level.txt