Metadata-Version: 2.1
Name: Leonov-1279
Version: 0.0.2
Summary: My Package
Author: Arseny
Author-email: j31leonov@gmail.com
